pytest_ponyorm.py
pytest_ponyorm-0.3.3.dist-info/METADATA
pytest_ponyorm-0.3.3.dist-info/RECORD
pytest_ponyorm-0.3.3.dist-info/WHEEL
pytest_ponyorm-0.3.3.dist-info/entry_points.txt
pytest_ponyorm-0.3.3.dist-info/top_level.txt
