Metadata-Version: 2.1
Name: pytest-ponyorm
Version: 0.3.3
Summary: PonyORM in Pytest
Home-page: https://github.com/jgirardet/pytest-ponyorm
Author: Jimmy Girardet
Author-email: ijkl@netc.fr
Maintainer: Jimmy Girardet
Maintainer-email: ijkl@netc.fr
License: GNU GPL v3.0
Platform: UNKNOWN
Classifier: Framework :: Pytest
Classifier: Intended Audience :: Developers
Classifier: Topic :: Software Development :: Testing
Classifier: Programming Language :: Python
Classifier: Programming Language :: Python :: 3.5
Classifier: Programming Language :: Python :: 3.6
Classifier: Programming Language :: Python :: Implementation :: CPython
Classifier: Programming Language :: Python :: Implementation :: PyPy
Classifier: Operating System :: OS Independent
Classifier: License :: OSI Approved :: GNU General Public License v3 (GPLv3)
Requires-Python: >=3.5
Requires-Dist: pytest (>=3.1.1)
